[{"line":2,"elements":[{"line":4,"name":"","description":"","type":"background","keyword":"Background","steps":[{"result":{"duration":82408200,"status":"passed"},"line":5,"name":"Utilisateur est sur la page d'accueil d'AliExpress","match":{"location":"stepdefinitions.menu.AliExpressStepDefinitions.utilisateur_est_sur_la_page_daccueil_dAliExpress()"},"keyword":"Given "},{"result":{"duration":14990300,"status":"passed"},"line":6,"name":"Utilisateur vérifie que l'URL est correcte","match":{"location":"stepdefinitions.menu.AliExpressStepDefinitions.utilisateur_vérifie_que_lURL_est_correctes()"},"keyword":"Then "},{"result":{"duration":107321300,"status":"passed"},"line":7,"name":"Utilisateur est sur la page Toutes les Catégories","match":{"location":"stepdefinitions.menu.AliExpressStepDefinitions.utilisateur_est_sur_la_page_Toutes_les_Catégories()"},"keyword":"Then "},{"result":{"duration":2085827000,"status":"passed"},"line":8,"name":"Utilisateur clique sur la catégorie \"Électroménager\"","match":{"arguments":[{"val":"\"Électroménager\"","offset":36}],"location":"stepdefinitions.menu.AliExpressStepDefinitions.utilisateur_clique_sur_la_catégorie(java.lang.String)"},"keyword":"When "}]},{"start_timestamp":"2024-10-03T12:51:53.604Z","before":[{"result":{"duration":7797139800,"status":"passed"},"match":{"location":"stepdefinitions.Hooks.beforeAll(io.cucumber.java.Scenario)"}}],"line":64,"name":"L'utilisateur peut visualiser les produits en mode liste","description":"","id":"categorie-d-électroménager;l-utilisateur-peut-visualiser-les-produits-en-mode-liste","after":[{"result":{"duration":274109300,"status":"passed"},"match":{"location":"stepdefinitions.Hooks.tearDown(io.cucumber.java.Scenario)"}}],"type":"scenario","keyword":"Scenario","steps":[{"result":{"duration":2894891900,"status":"passed"},"line":65,"name":"Utilisateur est sur la page d'une sous-catégorie sélectionnée","match":{"location":"stepdefinitions.menu.AliExpressStepDefinitions.utilisateur_est_sur_la_page_d_une_sous_catégorie_sélectionnée()"},"keyword":"Given "},{"result":{"duration":10262973000,"status":"passed"},"line":66,"name":"Utilisateur clique sur l'option \"List\"","match":{"arguments":[{"val":"\"List\"","offset":32}],"location":"stepdefinitions.menu.AliExpressStepDefinitions.utilisateur_clique_sur_l_option(java.lang.String)"},"keyword":"When "},{"result":{"duration":22384200,"status":"passed"},"line":67,"name":"Les produits doivent être affichés en mode \"List\"","match":{"arguments":[{"val":"\"List\"","offset":43}],"location":"stepdefinitions.menu.AliExpressStepDefinitions.les_produits_doivent_etre_affiches_en_mode(java.lang.String)"},"keyword":"Then "}],"tags":[{"name":"@web"}]}],"name":"Categorie d'Électroménager","description":"","id":"categorie-d-électroménager","keyword":"Feature","uri":"file:src/test/resources/features/Electromenager.feature","tags":[]}]